MANIFEST.in
Makefile
README.rst
buildout.cfg
plone-4.3.x.cfg
plone-5.1.x.cfg
plone-5.2.x.cfg
requirements.txt
setup.py
collective/__init__.py
collective.timedevents.egg-info/PKG-INFO
collective.timedevents.egg-info/SOURCES.txt
collective.timedevents.egg-info/dependency_links.txt
collective.timedevents.egg-info/entry_points.txt
collective.timedevents.egg-info/namespace_packages.txt
collective.timedevents.egg-info/not-zip-safe
collective.timedevents.egg-info/requires.txt
collective.timedevents.egg-info/top_level.txt
collective/timedevents/__init__.py
collective/timedevents/configure.zcml
collective/timedevents/events.py
collective/timedevents/interfaces.py
collective/timedevents/tests.py
collective/timedevents/views.py
docs/HISTORY.txt