Metadata-Version: 2.1
Name: collective.timedevents
Version: 1.1
Summary: Plone/Zope time based event mechanism
Home-page: http://plone.org/products/collective-timedevents
Author: Mikko Ohtamaa
Author-email: mikko.ohtamaa@twinapex.com
License: GPL
Keywords: plone zope event clock time subscriber date day
Platform: UNKNOWN
Classifier: Framework :: Plone
Classifier: Framework :: Plone :: 4.3
Classifier: Framework :: Plone :: 5.1
Classifier: Framework :: Plone :: 5.2
Classifier: Framework :: Plone :: Addon
Classifier: Programming Language :: Python
Classifier: Programming Language :: Python :: 2.7
Classifier: Programming Language :: Python :: 3.7
Classifier: Programming Language :: Python :: 3.8
Classifier: Topic :: Software Development :: Libraries :: Python Modules
Classifier: License :: OSI Approved :: GNU General Public License (GPL)
Classifier: Development Status :: 5 - Production/Stable
Provides-Extra: test
